{
  "id": "designer-form-switch-inline-props",
  "name": "designer-form-switch-inline-props",
  "title": "表单设计器下拉切换与内联表单属性",
  "description": "",
  "status": "completed",
  "dev_type": null,
  "scope": null,
  "package": null,
  "priority": "P2",
  "creator": "decade",
  "assignee": "decade",
  "createdAt": "2026-07-15",
  "completedAt": "2026-07-16",
  "branch": null,
  "base_branch": "draft",
  "worktree_path": null,
  "commit": null,
  "pr_url": null,
  "subtasks": [],
  "children": [],
  "parent": null,
  "relatedFiles": [],
  "notes": "",
  "meta": {}
}